{"Nodes":[],"ExecutionTime":"2023-08-19T05:02:14.2960395Z","GenerationTime":"0001-01-01T00:00:00","PluginUserSpecFlowId":"f0055c39-706e-4e5f-b864-4b73720c2b2f","CLIUserSpecFlowId":null,"ExecutionResults":[{"ContextType":"Scenario","FeatureFolderPath":"Features/Release 1/Sprint 1","FeatureTitle":"Navigation-Through-Different-Modules","ScenarioTitle":"Navigating to Clients Module","ScenarioArguments":[],"Status":"OK","StepResults":[{"Duration":"00:00:01.6479969","Status":"OK","Error":null,"Outputs":null},{"Duration":"00:00:00.1397020","Status":"OK","Error":null,"Outputs":null},{"Duration":"00:00:00.0076138","Status":"OK","Error":null,"Outputs":null}],"Outputs":null}],"StepReports":null}